{
  "meta": {
    "problem_id": "mamo_complex_79",
    "source": null,
    "description": "Optimize the logistics network by selecting distribution centers to open and determining shipping routes to minimize total costs.",
    "sense": "min",
    "version": 1
  },
  "sets": [
    {
      "name": "CENTERS",
      "elements": [
        "1",
        "2",
        "3",
        "4",
        "5",
        "6",
        "7",
        "8"
      ],
      "description": "Potential distribution centers"
    },
    {
      "name": "STORES",
      "elements": [
        "1",
        "2",
        "3",
        "4",
        "5",
        "6",
        "7",
        "8",
        "9"
      ],
      "description": "Retail stores needing supply"
    }
  ],
  "params": [
    {
      "name": "opening_cost",
      "indices": [
        "CENTERS"
      ],
      "values": {
        "1": 151000,
        "2": 192000,
        "3": 114000,
        "4": 171000,
        "5": 160000,
        "6": 120000,
        "7": 182000,
        "8": 186000
      },
      "description": "Opening costs for each distribution center"
    },
    {
      "name": "transport_cost",
      "indices": [
        "CENTERS",
        "STORES"
      ],
      "values": {
        "1": {
          "1": 3,
          "2": 3,
          "3": 5,
          "4": 4,
          "5": 3,
          "6": 5,
          "7": 2,
          "8": 4,
          "9": 2
        },
        "2": {
          "1": 4,
          "2": 5,
          "3": 1,
          "4": 4,
          "5": 2,
          "6": 5,
          "7": 4,
          "8": 1,
          "9": 1
        },
        "3": {
          "1": 3,
          "2": 3,
          "3": 2,
          "4": 4,
          "5": 4,
          "6": 3,
          "7": 4,
          "8": 4,
          "9": 1
        },
        "4": {
          "1": 3,
          "2": 5,
          "3": 3,
          "4": 5,
          "5": 1,
          "6": 2,
          "7": 4,
          "8": 1,
          "9": 4
        },
        "5": {
          "1": 2,
          "2": 2,
          "3": 1,
          "4": 2,
          "5": 5,
          "6": 2,
          "7": 4,
          "8": 4,
          "9": 4
        },
        "6": {
          "1": 4,
          "2": 5,
          "3": 3,
          "4": 1,
          "5": 4,
          "6": 2,
          "7": 4,
          "8": 2,
          "9": 2
        },
        "7": {
          "1": 4,
          "2": 5,
          "3": 2,
          "4": 2,
          "5": 4,
          "6": 2,
          "7": 2,
          "8": 4,
          "9": 4
        },
        "8": {
          "1": 1,
          "2": 5,
          "3": 5,
          "4": 2,
          "5": 5,
          "6": 2,
          "7": 1,
          "8": 4,
          "9": 4
        }
      },
      "description": "Transportation cost per unit from each distribution center to each store"
    },
    {
      "name": "demand",
      "indices": [
        "STORES"
      ],
      "values": {
        "1": 779,
        "2": 892,
        "3": 440,
        "4": 556,
        "5": 414,
        "6": 464,
        "7": 920,
        "8": 743,
        "9": 528
      },
      "description": "Demand of each retail store in units"
    },
    {
      "name": "capacity",
      "indices": [
        "CENTERS"
      ],
      "values": {
        "1": 1447,
        "2": 1886,
        "3": 1962,
        "4": 1392,
        "5": 1191,
        "6": 1218,
        "7": 1088,
        "8": 1178
      },
      "description": "Supply capacity of each distribution center in units"
    }
  ],
  "vars": [
    {
      "name": "open",
      "indices": [
        "CENTERS"
      ],
      "vartype": "binary",
      "lb": 0.0,
      "ub": 1.0,
      "description": "Binary variable indicating if a distribution center is open"
    },
    {
      "name": "ship",
      "indices": [
        "CENTERS",
        "STORES"
      ],
      "vartype": "continuous",
      "lb": 0.0,
      "ub": null,
      "description": "Amount of goods shipped from a distribution center to a store"
    }
  ],
  "objective": {
    "name": "min_total_cost",
    "sense": "min",
    "expr": "sum(open[c] * opening_cost[c] for c in CENTERS) + sum(ship[c][s] * transport_cost[c][s] for c in CENTERS for s in STORES)",
    "description": "Minimize the total cost of opening distribution centers and transporting goods"
  },
  "constraints": [
    {
      "name": "demand_satisfaction_store_1",
      "expr_lhs": "sum(ship[c]['1'] for c in CENTERS)",
      "sense": ">=",
      "expr_rhs": "demand['1']",
      "description": "Satisfy demand for store 1"
    },
    {
      "name": "demand_satisfaction_store_2",
      "expr_lhs": "sum(ship[c]['2'] for c in CENTERS)",
      "sense": ">=",
      "expr_rhs": "demand['2']",
      "description": "Satisfy demand for store 2"
    },
    {
      "name": "demand_satisfaction_store_3",
      "expr_lhs": "sum(ship[c]['3'] for c in CENTERS)",
      "sense": ">=",
      "expr_rhs": "demand['3']",
      "description": "Satisfy demand for store 3"
    },
    {
      "name": "demand_satisfaction_store_4",
      "expr_lhs": "sum(ship[c]['4'] for c in CENTERS)",
      "sense": ">=",
      "expr_rhs": "demand['4']",
      "description": "Satisfy demand for store 4"
    },
    {
      "name": "demand_satisfaction_store_5",
      "expr_lhs": "sum(ship[c]['5'] for c in CENTERS)",
      "sense": ">=",
      "expr_rhs": "demand['5']",
      "description": "Satisfy demand for store 5"
    },
    {
      "name": "demand_satisfaction_store_6",
      "expr_lhs": "sum(ship[c]['6'] for c in CENTERS)",
      "sense": ">=",
      "expr_rhs": "demand['6']",
      "description": "Satisfy demand for store 6"
    },
    {
      "name": "demand_satisfaction_store_7",
      "expr_lhs": "sum(ship[c]['7'] for c in CENTERS)",
      "sense": ">=",
      "expr_rhs": "demand['7']",
      "description": "Satisfy demand for store 7"
    },
    {
      "name": "demand_satisfaction_store_8",
      "expr_lhs": "sum(ship[c]['8'] for c in CENTERS)",
      "sense": ">=",
      "expr_rhs": "demand['8']",
      "description": "Satisfy demand for store 8"
    },
    {
      "name": "demand_satisfaction_store_9",
      "expr_lhs": "sum(ship[c]['9'] for c in CENTERS)",
      "sense": ">=",
      "expr_rhs": "demand['9']",
      "description": "Satisfy demand for store 9"
    },
    {
      "name": "capacity_limit_center_1",
      "expr_lhs": "sum(ship['1'][s] for s in STORES)",
      "sense": "<=",
      "expr_rhs": "capacity['1'] * open['1']",
      "description": "Capacity limit for center 1"
    },
    {
      "name": "capacity_limit_center_2",
      "expr_lhs": "sum(ship['2'][s] for s in STORES)",
      "sense": "<=",
      "expr_rhs": "capacity['2'] * open['2']",
      "description": "Capacity limit for center 2"
    },
    {
      "name": "capacity_limit_center_3",
      "expr_lhs": "sum(ship['3'][s] for s in STORES)",
      "sense": "<=",
      "expr_rhs": "capacity['3'] * open['3']",
      "description": "Capacity limit for center 3"
    },
    {
      "name": "capacity_limit_center_4",
      "expr_lhs": "sum(ship['4'][s] for s in STORES)",
      "sense": "<=",
      "expr_rhs": "capacity['4'] * open['4']",
      "description": "Capacity limit for center 4"
    },
    {
      "name": "capacity_limit_center_5",
      "expr_lhs": "sum(ship['5'][s] for s in STORES)",
      "sense": "<=",
      "expr_rhs": "capacity['5'] * open['5']",
      "description": "Capacity limit for center 5"
    },
    {
      "name": "capacity_limit_center_6",
      "expr_lhs": "sum(ship['6'][s] for s in STORES)",
      "sense": "<=",
      "expr_rhs": "capacity['6'] * open['6']",
      "description": "Capacity limit for center 6"
    },
    {
      "name": "capacity_limit_center_7",
      "expr_lhs": "sum(ship['7'][s] for s in STORES)",
      "sense": "<=",
      "expr_rhs": "capacity['7'] * open['7']",
      "description": "Capacity limit for center 7"
    },
    {
      "name": "capacity_limit_center_8",
      "expr_lhs": "sum(ship['8'][s] for s in STORES)",
      "sense": "<=",
      "expr_rhs": "capacity['8'] * open['8']",
      "description": "Capacity limit for center 8"
    }
  ],
  "graph": null
}