{
  "meta": {
    "problem_id": "red_star_plastic_factory",
    "source": null,
    "description": "Optimize the production of plastic containers to minimize total cost while meeting demand.",
    "sense": "min",
    "version": 1
  },
  "sets": [
    {
      "name": "CONTAINERS",
      "elements": [
        "1",
        "2",
        "3",
        "4",
        "5",
        "6"
      ],
      "description": "Types of plastic containers"
    }
  ],
  "params": [
    {
      "name": "capacity",
      "indices": [
        "CONTAINERS"
      ],
      "values": {
        "1": 1500,
        "2": 2500,
        "3": 4000,
        "4": 6000,
        "5": 9000,
        "6": 12000
      },
      "description": "Capacity of each container type in cm^3"
    },
    {
      "name": "demand",
      "indices": [
        "CONTAINERS"
      ],
      "values": {
        "1": 500,
        "2": 550,
        "3": 700,
        "4": 900,
        "5": 400,
        "6": 300
      },
      "description": "Demand for each container type in units"
    },
    {
      "name": "variable_cost",
      "indices": [
        "CONTAINERS"
      ],
      "values": {
        "1": 5,
        "2": 8,
        "3": 10,
        "4": 12,
        "5": 16,
        "6": 18
      },
      "description": "Variable cost per unit for each container type in ¥"
    },
    {
      "name": "fixed_cost",
      "indices": [],
      "values": 1200,
      "description": "Fixed cost for using equipment for each container type in ¥"
    }
  ],
  "vars": [
    {
      "name": "production",
      "indices": [
        "CONTAINERS"
      ],
      "vartype": "integer",
      "lb": 0,
      "ub": null,
      "description": "Number of units produced for each container type"
    },
    {
      "name": "use_equipment",
      "indices": [
        "CONTAINERS"
      ],
      "vartype": "binary",
      "lb": 0,
      "ub": 1,
      "description": "Binary variable indicating if equipment for a container type is used"
    }
  ],
  "objective": {
    "name": "min_total_cost",
    "sense": "min",
    "expr": "sum(variable_cost[c] * production[c] + fixed_cost * use_equipment[c] for c in CONTAINERS)",
    "description": "Minimize the total cost of production including variable and fixed costs"
  },
  "constraints": [
    {
      "name": "demand_1",
      "expr_lhs": "production['1'] + production['2'] + production['3'] + production['4'] + production['5'] + production['6']",
      "sense": ">=",
      "expr_rhs": "demand['1']",
      "description": "Meet demand for container type 1"
    },
    {
      "name": "demand_2",
      "expr_lhs": "production['2'] + production['3'] + production['4'] + production['5'] + production['6']",
      "sense": ">=",
      "expr_rhs": "demand['2']",
      "description": "Meet demand for container type 2"
    },
    {
      "name": "demand_3",
      "expr_lhs": "production['3'] + production['4'] + production['5'] + production['6']",
      "sense": ">=",
      "expr_rhs": "demand['3']",
      "description": "Meet demand for container type 3"
    },
    {
      "name": "demand_4",
      "expr_lhs": "production['4'] + production['5'] + production['6']",
      "sense": ">=",
      "expr_rhs": "demand['4']",
      "description": "Meet demand for container type 4"
    },
    {
      "name": "demand_5",
      "expr_lhs": "production['5'] + production['6']",
      "sense": ">=",
      "expr_rhs": "demand['5']",
      "description": "Meet demand for container type 5"
    },
    {
      "name": "demand_6",
      "expr_lhs": "production['6']",
      "sense": ">=",
      "expr_rhs": "demand['6']",
      "description": "Meet demand for container type 6"
    },
    {
      "name": "equipment_usage_1",
      "expr_lhs": "production['1']",
      "sense": "<=",
      "expr_rhs": "use_equipment['1'] * demand['1']",
      "description": "Equipment usage constraint for container type 1"
    },
    {
      "name": "equipment_usage_2",
      "expr_lhs": "production['2']",
      "sense": "<=",
      "expr_rhs": "use_equipment['2'] * demand['2']",
      "description": "Equipment usage constraint for container type 2"
    },
    {
      "name": "equipment_usage_3",
      "expr_lhs": "production['3']",
      "sense": "<=",
      "expr_rhs": "use_equipment['3'] * demand['3']",
      "description": "Equipment usage constraint for container type 3"
    },
    {
      "name": "equipment_usage_4",
      "expr_lhs": "production['4']",
      "sense": "<=",
      "expr_rhs": "use_equipment['4'] * demand['4']",
      "description": "Equipment usage constraint for container type 4"
    },
    {
      "name": "equipment_usage_5",
      "expr_lhs": "production['5']",
      "sense": "<=",
      "expr_rhs": "use_equipment['5'] * demand['5']",
      "description": "Equipment usage constraint for container type 5"
    },
    {
      "name": "equipment_usage_6",
      "expr_lhs": "production['6']",
      "sense": "<=",
      "expr_rhs": "use_equipment['6'] * demand['6']",
      "description": "Equipment usage constraint for container type 6"
    }
  ],
  "graph": null
}